{
  "edges": [
    {
      "predicate": "in",
      "source": "flour1",
      "target": "bowl1"
    },
    {
      "predicate": "on",
      "source": "chicken1",
      "target": "flour1"
    },
    {
      "predicate": "next_to",
      "source": "bowl1",
      "target": "bowl2"
    },
    {
      "predicate": "behind",
      "source": "glass_bowl1",
      "target": "bowl1"
    },
    {
      "predicate": "right_of",
      "source": "wire_rack1",
      "target": "bowl1"
    }
  ],
  "nodes": [
    {
      "attributes": {
        "appearance": "white ceramic",
        "size": "medium"
      },
      "id": "bowl1",
      "label": "White Bowl",
      "location": "0.35,0.18,0.94,0.76,0.9"
    },
    {
      "attributes": {
        "appearance": "white powder",
        "size": "large"
      },
      "id": "flour1",
      "label": "Flour",
      "location": "0.40,0.25,0.90,0.70,0.8"
    },
    {
      "attributes": {
        "appearance": "pink raw meat",
        "size": "small"
      },
      "id": "chicken1",
      "label": "Chicken Piece",
      "location": "0.60,0.35,0.75,0.50,0.85"
    },
    {
      "attributes": {
        "appearance": "transparent glass",
        "size": "medium"
      },
      "id": "glass_bowl1",
      "label": "Glass Bowl",
      "location": "0.05,0.00,0.60,0.30,0.8"
    },
    {
      "attributes": {
        "appearance": "white ceramic",
        "size": "medium"
      },
      "id": "bowl2",
      "label": "White Bowl",
      "location": "0.45,0.75,0.95,0.98,0.8"
    },
    {
      "attributes": {
        "appearance": "metal grid",
        "size": "medium"
      },
      "id": "wire_rack1",
      "label": "Wire Rack",
      "location": "0.75,0.00,1.00,0.40,0.7"
    }
  ]
}