{
  "edges": [
    {
      "predicate": "left_of",
      "source": "strip1",
      "target": "strip2"
    },
    {
      "predicate": "right_of",
      "source": "strip3",
      "target": "strip4"
    },
    {
      "predicate": "above",
      "source": "strip5",
      "target": "strip6"
    },
    {
      "predicate": "next_to",
      "source": "strip7",
      "target": "strip8"
    },
    {
      "predicate": "below",
      "source": "strip9",
      "target": "strip10"
    }
  ],
  "nodes": [
    {
      "attributes": {
        "appearance": "pink gradient",
        "size": "medium"
      },
      "id": "strip1",
      "label": "horizontal strip",
      "location": "0.00,0.00,0.10,1.00,0.9"
    },
    {
      "attributes": {
        "appearance": "beige gradient",
        "size": "small"
      },
      "id": "strip2",
      "label": "vertical strip",
      "location": "0.10,0.00,0.15,1.00,0.9"
    },
    {
      "attributes": {
        "appearance": "grey solid",
        "size": "small"
      },
      "id": "strip3",
      "label": "horizontal strip",
      "location": "0.15,0.20,0.20,0.30,0.9"
    },
    {
      "attributes": {
        "appearance": "purple solid",
        "size": "small"
      },
      "id": "strip4",
      "label": "horizontal strip",
      "location": "0.20,0.20,0.80,0.30,0.9"
    },
    {
      "attributes": {
        "appearance": "pink gradient",
        "size": "medium"
      },
      "id": "strip5",
      "label": "horizontal strip",
      "location": "0.00,0.60,0.10,1.00,0.9"
    },
    {
      "attributes": {
        "appearance": "beige gradient",
        "size": "small"
      },
      "id": "strip6",
      "label": "vertical strip",
      "location": "0.10,0.60,0.15,1.00,0.9"
    },
    {
      "attributes": {
        "appearance": "grey solid",
        "size": "small"
      },
      "id": "strip7",
      "label": "horizontal strip",
      "location": "0.15,0.40,0.20,0.50,0.9"
    },
    {
      "attributes": {
        "appearance": "purple solid",
        "size": "small"
      },
      "id": "strip8",
      "label": "horizontal strip",
      "location": "0.20,0.40,0.80,0.50,0.9"
    },
    {
      "attributes": {
        "appearance": "pink gradient",
        "size": "large"
      },
      "id": "strip9",
      "label": "horizontal strip",
      "location": "0.00,0.00,1.00,0.20,0.9"
    },
    {
      "attributes": {
        "appearance": "purple solid",
        "size": "large"
      },
      "id": "strip10",
      "label": "horizontal strip",
      "location": "0.00,0.20,1.00,0.40,0.9"
    }
  ]
}