{
  "edges": [
    {
      "predicate": "holding",
      "source": "person1",
      "target": "knife1"
    },
    {
      "predicate": "on",
      "source": "knife1",
      "target": "board1"
    },
    {
      "predicate": "on",
      "source": "butter1",
      "target": "board1"
    },
    {
      "predicate": "on",
      "source": "bread1",
      "target": "board1"
    },
    {
      "predicate": "on",
      "source": "lettuce1",
      "target": "plate1"
    },
    {
      "predicate": "on",
      "source": "plate1",
      "target": "counter1"
    },
    {
      "predicate": "on",
      "source": "blender1",
      "target": "counter1"
    },
    {
      "predicate": "on",
      "source": "jar1",
      "target": "shelf1"
    },
    {
      "predicate": "on",
      "source": "fruit_bowl1",
      "target": "shelf1"
    },
    {
      "predicate": "on",
      "source": "stool1",
      "target": "counter1"
    },
    {
      "predicate": "on",
      "source": "stool2",
      "target": "counter1"
    },
    {
      "predicate": "on",
      "source": "lamp1",
      "target": "counter1"
    },
    {
      "predicate": "attached_to",
      "source": "hanging_pots1",
      "target": "wall1"
    },
    {
      "predicate": "in_front_of",
      "source": "person1",
      "target": "wall1"
    }
  ],
  "nodes": [
    {
      "attributes": {
        "appearance": "blue red plaid shirt",
        "size": "large"
      },
      "id": "person1",
      "label": "man",
      "location": "0.45,0.05,0.98,0.76,0.9"
    },
    {
      "attributes": {
        "appearance": "black plastic",
        "size": "medium"
      },
      "id": "blender1",
      "label": "stand blender",
      "location": "0.30,0.40,0.45,0.75,0.8"
    },
    {
      "attributes": {
        "appearance": "wooden",
        "size": "small"
      },
      "id": "board1",
      "label": "cutting board",
      "location": "0.45,0.60,0.75,0.85,0.8"
    },
    {
      "attributes": {
        "appearance": "metal blade black handle",
        "size": "small"
      },
      "id": "knife1",
      "label": "knife",
      "location": "0.55,0.55,0.75,0.70,0.8"
    },
    {
      "attributes": {
        "appearance": "yellow plastic",
        "size": "small"
      },
      "id": "butter1",
      "label": "butter container",
      "location": "0.50,0.65,0.55,0.75,0.8"
    },
    {
      "attributes": {
        "appearance": "brown bread",
        "size": "small"
      },
      "id": "bread1",
      "label": "bread slices",
      "location": "0.60,0.65,0.70,0.75,0.8"
    },
    {
      "attributes": {
        "appearance": "green leafy",
        "size": "small"
      },
      "id": "lettuce1",
      "label": "lettuce leaves",
      "location": "0.50,0.75,0.80,0.90,0.8"
    },
    {
      "attributes": {
        "appearance": "black ceramic",
        "size": "medium"
      },
      "id": "plate1",
      "label": "plate",
      "location": "0.45,0.75,0.80,0.95,0.8"
    },
    {
      "attributes": {
        "appearance": "dark wood",
        "size": "large"
      },
      "id": "counter1",
      "label": "countertop",
      "location": "0.00,0.60,1.00,1.00,0.9"
    },
    {
      "attributes": {
        "appearance": "grey stone",
        "size": "large"
      },
      "id": "wall1",
      "label": "brick wall",
      "location": "0.00,0.00,1.00,0.40,0.9"
    },
    {
      "attributes": {
        "appearance": "white metal",
        "size": "medium"
      },
      "id": "hanging_pots1",
      "label": "hanging pots",
      "location": "0.40,0.00,0.60,0.20,0.8"
    },
    {
      "attributes": {
        "appearance": "wooden",
        "size": "small"
      },
      "id": "stool1",
      "label": "bar stool",
      "location": "0.05,0.45,0.20,0.75,0.8"
    },
    {
      "attributes": {
        "appearance": "wooden",
        "size": "small"
      },
      "id": "stool2",
      "label": "bar stool",
      "location": "0.20,0.45,0.35,0.75,0.8"
    },
    {
      "attributes": {
        "appearance": "glass jars",
        "size": "small"
      },
      "id": "jar1",
      "label": "spice jars",
      "location": "0.00,0.30,0.30,0.45,0.8"
    },
    {
      "attributes": {
        "appearance": "wooden bowl",
        "size": "small"
      },
      "id": "fruit_bowl1",
      "label": "fruit bowl",
      "location": "0.30,0.30,0.45,0.45,0.8"
    },
    {
      "attributes": {
        "appearance": "white shade wooden stand",
        "size": "medium"
      },
      "id": "lamp1",
      "label": "floor lamp",
      "location": "0.85,0.20,1.00,0.80,0.8"
    },
    {
      "attributes": {
        "appearance": "dark wood",
        "size": "medium"
      },
      "id": "shelf1",
      "label": "shelf",
      "location": "0.00,0.00,1.00,0.20,0.8"
    }
  ]
}