{
  "edges": [
    {
      "predicate": "holding",
      "source": "person1",
      "target": "fork1"
    },
    {
      "predicate": "on",
      "source": "pancake_stack1",
      "target": "plate1"
    },
    {
      "predicate": "next_to",
      "source": "pancake_stack2",
      "target": "pancake_stack1"
    },
    {
      "predicate": "left_of",
      "source": "griddle1",
      "target": "plate1"
    },
    {
      "predicate": "right_of",
      "source": "pitcher1",
      "target": "plate1"
    },
    {
      "predicate": "in_front_of",
      "source": "person1",
      "target": "stove1"
    },
    {
      "predicate": "behind",
      "source": "cabinet1",
      "target": "person1"
    },
    {
      "predicate": "behind",
      "source": "dishwasher1",
      "target": "person1"
    },
    {
      "predicate": "on",
      "source": "cutting_board1",
      "target": "countertop1"
    },
    {
      "predicate": "on",
      "source": "pepper_shaker1",
      "target": "countertop1"
    },
    {
      "predicate": "on",
      "source": "salt_shaker1",
      "target": "countertop1"
    },
    {
      "predicate": "on",
      "source": "butter_plate1",
      "target": "countertop1"
    }
  ],
  "nodes": [
    {
      "attributes": {
        "appearance": "purple top white apron",
        "size": "large"
      },
      "id": "person1",
      "label": "woman",
      "location": "0.35,0.0,0.65,0.8,0.9"
    },
    {
      "attributes": {
        "appearance": "silver metal",
        "size": "small"
      },
      "id": "fork1",
      "label": "fork",
      "location": "0.47,0.45,0.55,0.6,0.8"
    },
    {
      "attributes": {
        "appearance": "white ceramic",
        "size": "medium"
      },
      "id": "plate1",
      "label": "plate",
      "location": "0.45,0.55,0.6,0.75,0.9"
    },
    {
      "attributes": {
        "appearance": "golden brown",
        "size": "small"
      },
      "id": "pancake_stack1",
      "label": "pancakes",
      "location": "0.5,0.6,0.6,0.75,0.9"
    },
    {
      "attributes": {
        "appearance": "white ceramic",
        "size": "medium"
      },
      "id": "plate2",
      "label": "plate",
      "location": "0.1,0.75,0.4,0.95,0.9"
    },
    {
      "attributes": {
        "appearance": "golden brown",
        "size": "small"
      },
      "id": "pancake_stack2",
      "label": "pancakes",
      "location": "0.15,0.8,0.35,0.9,0.9"
    },
    {
      "attributes": {
        "appearance": "black metal",
        "size": "large"
      },
      "id": "griddle1",
      "label": "griddle",
      "location": "0.0,0.6,0.3,0.9,0.9"
    },
    {
      "attributes": {
        "appearance": "light wood",
        "size": "large"
      },
      "id": "countertop1",
      "label": "countertop",
      "location": "0.0,0.5,1.0,1.0,0.9"
    },
    {
      "attributes": {
        "appearance": "wooden",
        "size": "medium"
      },
      "id": "cutting_board1",
      "label": "cutting board",
      "location": "0.75,0.0,0.95,0.2,0.8"
    },
    {
      "attributes": {
        "appearance": "glass with black lid",
        "size": "small"
      },
      "id": "pepper_shaker1",
      "label": "pepper shaker",
      "location": "0.85,0.1,0.9,0.25,0.8"
    },
    {
      "attributes": {
        "appearance": "glass with white lid",
        "size": "small"
      },
      "id": "salt_shaker1",
      "label": "salt shaker",
      "location": "0.9,0.1,0.95,0.25,0.8"
    },
    {
      "attributes": {
        "appearance": "metallic grey",
        "size": "large"
      },
      "id": "dishwasher1",
      "label": "dishwasher",
      "location": "0.7,0.3,0.95,0.6,0.9"
    },
    {
      "attributes": {
        "appearance": "brown wood",
        "size": "large"
      },
      "id": "cabinet1",
      "label": "kitchen cabinet",
      "location": "0.0,0.2,0.4,0.6,0.9"
    },
    {
      "attributes": {
        "appearance": "black metal",
        "size": "large"
      },
      "id": "stove1",
      "label": "stove",
      "location": "0.0,0.0,0.4,0.4,0.9"
    },
    {
      "attributes": {
        "appearance": "beige ceramic",
        "size": "medium"
      },
      "id": "pitcher1",
      "label": "pitcher",
      "location": "0.75,0.6,0.9,0.8,0.9"
    },
    {
      "attributes": {
        "appearance": "red plate with butter",
        "size": "small"
      },
      "id": "butter_plate1",
      "label": "butter plate",
      "location": "0.8,0.85,0.95,0.95,0.9"
    }
  ]
}