{
  "edges": [
    {
      "predicate": "holding",
      "source": "person1",
      "target": "spatula1"
    },
    {
      "predicate": "on",
      "source": "plate1",
      "target": "table1"
    },
    {
      "predicate": "on",
      "source": "bowl1",
      "target": "table1"
    },
    {
      "predicate": "on",
      "source": "salad_bowl",
      "target": "table1"
    },
    {
      "predicate": "on",
      "source": "tongs1",
      "target": "salad_bowl"
    },
    {
      "predicate": "on",
      "source": "lettuce1",
      "target": "salad_bowl"
    },
    {
      "predicate": "on",
      "source": "croutons1",
      "target": "bowl1"
    },
    {
      "predicate": "next_to",
      "source": "bowl1",
      "target": "plate1"
    },
    {
      "predicate": "behind",
      "source": "person1",
      "target": "table1"
    }
  ],
  "nodes": [
    {
      "attributes": {
        "appearance": "white lace apron",
        "size": "large"
      },
      "id": "person1",
      "label": "woman",
      "location": "0.35,0.0,0.65,0.7,0.9"
    },
    {
      "attributes": {
        "appearance": "transparent glass",
        "size": "medium"
      },
      "id": "bowl1",
      "label": "glass bowl",
      "location": "0.05,0.65,0.3,0.85,0.8"
    },
    {
      "attributes": {
        "appearance": "white ceramic",
        "size": "small"
      },
      "id": "plate1",
      "label": "plate",
      "location": "0.25,0.45,0.45,0.65,0.8"
    },
    {
      "attributes": {
        "appearance": "clear plastic",
        "size": "medium"
      },
      "id": "salad_bowl",
      "label": "salad bowl",
      "location": "0.6,0.55,0.9,0.9,0.9"
    },
    {
      "attributes": {
        "appearance": "red metal",
        "size": "medium"
      },
      "id": "tongs1",
      "label": "tongs",
      "location": "0.7,0.45,0.9,0.85,0.8"
    },
    {
      "attributes": {
        "appearance": "green leafy",
        "size": "small"
      },
      "id": "lettuce1",
      "label": "lettuce leaves",
      "location": "0.75,0.6,0.9,0.85,0.8"
    },
    {
      "attributes": {
        "appearance": "brown crispy",
        "size": "small"
      },
      "id": "croutons1",
      "label": "croutons",
      "location": "0.1,0.7,0.3,0.9,0.8"
    },
    {
      "attributes": {
        "appearance": "silver metal",
        "size": "small"
      },
      "id": "spatula1",
      "label": "spatula",
      "location": "0.4,0.3,0.6,0.5,0.8"
    },
    {
      "attributes": {
        "appearance": "wooden surface",
        "size": "large"
      },
      "id": "table1",
      "label": "table",
      "location": "0.0,0.5,1.0,1.0,0.9"
    }
  ]
}