{
  "edges": [
    {
      "predicate": "on",
      "source": "logo1",
      "target": "background1"
    },
    {
      "predicate": "on",
      "source": "text1",
      "target": "background1"
    },
    {
      "predicate": "on",
      "source": "image1",
      "target": "background1"
    },
    {
      "predicate": "on",
      "source": "image2",
      "target": "background1"
    },
    {
      "predicate": "next_to",
      "source": "cinnamon1",
      "target": "pepper1"
    },
    {
      "predicate": "left_of",
      "source": "cinnamon1",
      "target": "pepper1"
    },
    {
      "predicate": "right_of",
      "source": "samosa1",
      "target": "pakoda1"
    }
  ],
  "nodes": [
    {
      "attributes": {
        "appearance": "blue circle with white text",
        "size": "medium"
      },
      "id": "logo1",
      "label": "Rajshri Food Logo",
      "location": "0.45,0.03,0.55,0.28,0.9"
    },
    {
      "attributes": {
        "appearance": "white background with blue text",
        "size": "small"
      },
      "id": "text1",
      "label": "Food Text Overlay",
      "location": "0.47,0.36,0.53,0.44,0.8"
    },
    {
      "attributes": {
        "appearance": "black frame with golden fried food",
        "size": "medium"
      },
      "id": "image1",
      "label": "Pakoda Image",
      "location": "0.05,0.55,0.45,0.95,0.85"
    },
    {
      "attributes": {
        "appearance": "black frame with golden fried food",
        "size": "medium"
      },
      "id": "image2",
      "label": "Samosa Image",
      "location": "0.55,0.55,0.95,0.95,0.85"
    },
    {
      "attributes": {
        "appearance": "brown cinnamon sticks",
        "size": "large"
      },
      "id": "cinnamon1",
      "label": "Cinnamon Sticks",
      "location": "0.0,0.1,0.5,0.5,0.7"
    },
    {
      "attributes": {
        "appearance": "red pepper",
        "size": "medium"
      },
      "id": "pepper1",
      "label": "Red Pepper",
      "location": "0.6,0.1,0.9,0.5,0.7"
    },
    {
      "attributes": {
        "appearance": "golden brown fried",
        "size": "medium"
      },
      "id": "pakoda1",
      "label": "Potato Onion Fritters",
      "location": "0.05,0.55,0.45,0.95,0.8"
    },
    {
      "attributes": {
        "appearance": "golden brown fried",
        "size": "medium"
      },
      "id": "samosa1",
      "label": "Samosa",
      "location": "0.55,0.55,0.95,0.95,0.8"
    },
    {
      "attributes": {
        "appearance": "beige speckled",
        "size": "large"
      },
      "id": "background1",
      "label": "Background",
      "location": "0.0,0.0,1.0,1.0,0.6"
    }
  ]
}