{
  "edges": [
    {
      "predicate": "holding",
      "source": "tongs1",
      "target": "chicken1"
    },
    {
      "predicate": "in",
      "source": "flour1",
      "target": "tray1"
    },
    {
      "predicate": "on",
      "source": "chicken1",
      "target": "flour1"
    }
  ],
  "nodes": [
    {
      "attributes": {
        "appearance": "silver metal",
        "size": "large"
      },
      "id": "tray1",
      "label": "baking tray",
      "location": "0.0,0.0,1.0,1.0,0.95"
    },
    {
      "attributes": {
        "appearance": "beige powder",
        "size": "medium"
      },
      "id": "flour1",
      "label": "flour",
      "location": "0.0,0.1,1.0,0.8,0.85"
    },
    {
      "attributes": {
        "appearance": "black metal",
        "size": "medium"
      },
      "id": "tongs1",
      "label": "metal tongs",
      "location": "0.0,0.3,0.6,0.4,0.9"
    },
    {
      "attributes": {
        "appearance": "raw pinkish",
        "size": "small"
      },
      "id": "chicken1",
      "label": "raw chicken pieces",
      "location": "0.3,0.4,0.7,0.7,0.9"
    }
  ]
}