{
  "edges": [
    {
      "predicate": "holding",
      "source": "person1",
      "target": "bag1"
    },
    {
      "predicate": "on",
      "source": "board1",
      "target": "table1"
    },
    {
      "predicate": "on",
      "source": "bowl1",
      "target": "table1"
    },
    {
      "predicate": "next_to",
      "source": "towel1",
      "target": "bowl1"
    },
    {
      "predicate": "behind",
      "source": "wall1",
      "target": "person1"
    },
    {
      "predicate": "in_front_of",
      "source": "person1",
      "target": "wall1"
    }
  ],
  "nodes": [
    {
      "attributes": {
        "appearance": "green striped shirt",
        "size": "large"
      },
      "id": "person1",
      "label": "person",
      "location": "0.0,0.0,0.6,0.75,0.9"
    },
    {
      "attributes": {
        "appearance": "transparent plastic with brown powder",
        "size": "medium"
      },
      "id": "bag1",
      "label": "plastic bag",
      "location": "0.3,0.0,0.8,0.4,0.8"
    },
    {
      "attributes": {
        "appearance": "wooden",
        "size": "large"
      },
      "id": "board1",
      "label": "cutting board",
      "location": "0.0,0.6,1.0,0.8,0.9"
    },
    {
      "attributes": {
        "appearance": "clear glass",
        "size": "small"
      },
      "id": "bowl1",
      "label": "glass bowl",
      "location": "0.7,0.5,0.95,0.75,0.8"
    },
    {
      "attributes": {
        "appearance": "white cloth",
        "size": "small"
      },
      "id": "towel1",
      "label": "kitchen towel",
      "location": "0.45,0.6,0.6,0.75,0.7"
    },
    {
      "attributes": {
        "appearance": "light grey surface",
        "size": "large"
      },
      "id": "table1",
      "label": "table",
      "location": "0.0,0.75,1.0,1.0,0.9"
    },
    {
      "attributes": {
        "appearance": "white painted",
        "size": "large"
      },
      "id": "wall1",
      "label": "wall",
      "location": "0.0,0.0,1.0,0.6,0.9"
    }
  ]
}