{
  "edges": [
    {
      "predicate": "holding",
      "source": "person1",
      "target": "whisk1"
    },
    {
      "predicate": "in",
      "source": "whisk1",
      "target": "bowl1"
    },
    {
      "predicate": "on",
      "source": "bowl1",
      "target": "countertop1"
    },
    {
      "predicate": "on",
      "source": "pan1",
      "target": "stove1"
    },
    {
      "predicate": "on",
      "source": "stove1",
      "target": "countertop1"
    },
    {
      "predicate": "next_to",
      "source": "knife_block1",
      "target": "sink1"
    },
    {
      "predicate": "behind",
      "source": "window1",
      "target": "person1"
    },
    {
      "predicate": "attached_to",
      "source": "plant_hanger1",
      "target": "window1"
    },
    {
      "predicate": "left_of",
      "source": "utensil_holder1",
      "target": "window1"
    },
    {
      "predicate": "right_of",
      "source": "fridge1",
      "target": "window1"
    }
  ],
  "nodes": [
    {
      "attributes": {
        "appearance": "pink shirt blue apron",
        "size": "large"
      },
      "id": "person1",
      "label": "woman",
      "location": "0.35,0.18,0.75,0.9,0.9"
    },
    {
      "attributes": {
        "appearance": "metal bowl white mixture",
        "size": "small"
      },
      "id": "bowl1",
      "label": "mixing bowl",
      "location": "0.45,0.6,0.55,0.7,0.8"
    },
    {
      "attributes": {
        "appearance": "silver metal",
        "size": "small"
      },
      "id": "whisk1",
      "label": "whisk",
      "location": "0.42,0.55,0.5,0.7,0.8"
    },
    {
      "attributes": {
        "appearance": "wooden block black handles",
        "size": "medium"
      },
      "id": "knife_block1",
      "label": "knife block",
      "location": "0.1,0.5,0.2,0.7,0.8"
    },
    {
      "attributes": {
        "appearance": "white ceramic",
        "size": "medium"
      },
      "id": "sink1",
      "label": "sink",
      "location": "0.2,0.45,0.4,0.6,0.8"
    },
    {
      "attributes": {
        "appearance": "red metal",
        "size": "medium"
      },
      "id": "pan1",
      "label": "frying pan",
      "location": "0.7,0.65,0.9,0.8,0.8"
    },
    {
      "attributes": {
        "appearance": "black glass",
        "size": "medium"
      },
      "id": "stove1",
      "label": "gas stove",
      "location": "0.5,0.6,0.8,0.8,0.8"
    },
    {
      "attributes": {
        "appearance": "grey surface",
        "size": "large"
      },
      "id": "countertop1",
      "label": "countertop",
      "location": "0.0,0.5,1.0,0.8,0.8"
    },
    {
      "attributes": {
        "appearance": "white frame",
        "size": "large"
      },
      "id": "window1",
      "label": "window",
      "location": "0.0,0.0,1.0,0.5,0.8"
    },
    {
      "attributes": {
        "appearance": "green leaves red pot",
        "size": "small"
      },
      "id": "plant_hanger1",
      "label": "hanging plant",
      "location": "0.2,0.0,0.4,0.3,0.7"
    },
    {
      "attributes": {
        "appearance": "metal rack with utensils",
        "size": "small"
      },
      "id": "utensil_holder1",
      "label": "utensil holder",
      "location": "0.0,0.0,0.2,0.3,0.7"
    },
    {
      "attributes": {
        "appearance": "white metal",
        "size": "large"
      },
      "id": "fridge1",
      "label": "refrigerator",
      "location": "0.8,0.0,1.0,1.0,0.8"
    }
  ]
}