{
  "edges": [
    {
      "predicate": "next_to",
      "source": "person1",
      "target": "person2"
    },
    {
      "predicate": "in_front_of",
      "source": "person1",
      "target": "window"
    },
    {
      "predicate": "in_front_of",
      "source": "person2",
      "target": "window"
    },
    {
      "predicate": "on",
      "source": "bowl",
      "target": "countertop"
    },
    {
      "predicate": "on",
      "source": "napkin",
      "target": "countertop"
    },
    {
      "predicate": "attached_to",
      "source": "faucet",
      "target": "sink"
    },
    {
      "predicate": "behind",
      "source": "sink",
      "target": "bowl"
    },
    {
      "predicate": "left_of",
      "source": "cabinet_left",
      "target": "oven"
    },
    {
      "predicate": "right_of",
      "source": "oven",
      "target": "cabinet_right"
    },
    {
      "predicate": "includes",
      "source": "window",
      "target": "trees"
    }
  ],
  "nodes": [
    {
      "attributes": {
        "appearance": "bearded black shirt",
        "size": "large"
      },
      "id": "person1",
      "label": "man",
      "location": "0.05,0.0,0.48,0.93,0.9"
    },
    {
      "attributes": {
        "appearance": "black t-shirt",
        "size": "large"
      },
      "id": "person2",
      "label": "man",
      "location": "0.52,0.0,0.97,0.93,0.9"
    },
    {
      "attributes": {
        "appearance": "stainless steel",
        "size": "medium"
      },
      "id": "sink",
      "label": "sink",
      "location": "0.0,0.6,0.3,0.9,0.8"
    },
    {
      "attributes": {
        "appearance": "silver metal",
        "size": "small"
      },
      "id": "bowl",
      "label": "mixing bowl",
      "location": "0.0,0.8,0.3,1.0,0.8"
    },
    {
      "attributes": {
        "appearance": "blue cloth",
        "size": "small"
      },
      "id": "napkin",
      "label": "napkin",
      "location": "0.0,0.7,0.3,0.85,0.7"
    },
    {
      "attributes": {
        "appearance": "wooden brown",
        "size": "large"
      },
      "id": "cabinet_left",
      "label": "kitchen cabinet",
      "location": "0.0,0.0,0.3,0.6,0.8"
    },
    {
      "attributes": {
        "appearance": "wooden brown",
        "size": "large"
      },
      "id": "cabinet_right",
      "label": "kitchen cabinet",
      "location": "0.7,0.0,1.0,0.6,0.8"
    },
    {
      "attributes": {
        "appearance": "stainless steel",
        "size": "large"
      },
      "id": "oven",
      "label": "oven",
      "location": "0.6,0.1,0.9,0.6,0.8"
    },
    {
      "attributes": {
        "appearance": "glass",
        "size": "large"
      },
      "id": "window",
      "label": "window",
      "location": "0.0,0.0,0.6,0.6,0.9"
    },
    {
      "attributes": {
        "appearance": "green foliage",
        "size": "large"
      },
      "id": "trees",
      "label": "trees",
      "location": "0.0,0.0,0.6,0.6,0.7"
    },
    {
      "attributes": {
        "appearance": "pink text",
        "size": "small"
      },
      "id": "logo",
      "label": "TASTED logo",
      "location": "0.85,0.8,1.0,1.0,0.9"
    }
  ]
}