{
  "edges": [
    {
      "predicate": "holding",
      "source": "person1",
      "target": "burger1"
    },
    {
      "predicate": "holding",
      "source": "person2",
      "target": "burger2"
    },
    {
      "predicate": "next_to",
      "source": "person1",
      "target": "person2"
    },
    {
      "predicate": "in_front_of",
      "source": "person1",
      "target": "wall1"
    },
    {
      "predicate": "in_front_of",
      "source": "person2",
      "target": "wall1"
    },
    {
      "predicate": "on",
      "source": "logo1",
      "target": "table1"
    }
  ],
  "nodes": [
    {
      "attributes": {
        "appearance": "light skin red beard black shirt",
        "size": "large"
      },
      "id": "person1",
      "label": "man",
      "location": "0.0,0.0,0.5,1.0,0.9"
    },
    {
      "attributes": {
        "appearance": "light skin black shirt",
        "size": "large"
      },
      "id": "person2",
      "label": "man",
      "location": "0.4,0.0,1.0,1.0,0.9"
    },
    {
      "attributes": {
        "appearance": "green lettuce bun",
        "size": "small"
      },
      "id": "burger1",
      "label": "burger",
      "location": "0.1,0.3,0.3,0.6,0.8"
    },
    {
      "attributes": {
        "appearance": "brown bun",
        "size": "small"
      },
      "id": "burger2",
      "label": "burger",
      "location": "0.5,0.0,0.7,0.2,0.8"
    },
    {
      "attributes": {
        "appearance": "pink text",
        "size": "small"
      },
      "id": "logo1",
      "label": "TASTED logo",
      "location": "0.8,0.8,1.0,1.0,0.7"
    },
    {
      "attributes": {
        "appearance": "wooden brown",
        "size": "large"
      },
      "id": "table1",
      "label": "table",
      "location": "0.0,0.8,1.0,1.0,0.6"
    },
    {
      "attributes": {
        "appearance": "beige brick",
        "size": "large"
      },
      "id": "wall1",
      "label": "wall",
      "location": "0.0,0.0,1.0,0.5,0.6"
    }
  ]
}